License.txt
MANIFEST.in
README.txt
ez_setup.py
setup.cfg
setup.py
tests/__init__.py
tests/tests.py
ymap/__init__.py
ymap/ymap.py
ymap.egg-info/PKG-INFO
ymap.egg-info/SOURCES.txt
ymap.egg-info/dependency_links.txt
ymap.egg-info/entry_points.txt
ymap.egg-info/not-zip-safe
ymap.egg-info/requires.txt
ymap.egg-info/top_level.txt
ymap/data/PTMcode+PTMfunc_data/3DID_aceksites_interfaceRes_sc.txt
ymap/data/PTMcode+PTMfunc_data/3DID_phosphosites_interfaceRes_sc.txt
ymap/data/PTMcode+PTMfunc_data/3DID_ubisites_interfaceRessc_sc.txt
ymap/data/PTMcode+PTMfunc_data/SC_acet_interactions.txt
ymap/data/PTMcode+PTMfunc_data/SC_psites_interactions_sc.txt
ymap/data/PTMcode+PTMfunc_data/SC_ubi_interactions_sc.txt
ymap/data/PTMcode+PTMfunc_data/sc_btw_proteins.txt.zip
ymap/data/PTMcode+PTMfunc_data/sc_within_proteins.txt
ymap/data/PTMcode+PTMfunc_data/schotspot_updated.txt
ymap/example_mutation_files/mutated_proteins.txt
ymap/example_mutation_files/mutation.txt