Metadata-Version: 1.1
Name: ymap
Version: 2.0.8
Summary: An automated method to map yeast variants to protein modifications and functional regions
Home-page: https://github.com/CSB-KUL/yMap
Author: Ahmed Arslan
Author-email: ahmed.arslan@kuleuven.be
License: MIT
Keywords: Biofinformatics,Proteins variants,PostTransational-Modifications (PTMs),Proteins domains,Secondary Structures,Protein-Protein Interactions,Genomics,Proteomics,Gene Ontology,yMap
Platform: UNKNOWN
Classifier: Intended Audience :: Science/Research
Classifier: Topic :: Education
Classifier: License :: OSI Approved :: MIT License
Classifier: Programming Language :: Python :: 2.7
Classifier: Programming Language :: Python :: 3
Classifier: Programming Language :: Python :: 3.3
Classifier: Programming Language :: Python :: 3.4
Classifier: Programming Language :: Python :: 3.5
